{
	"configurations" : 
	[
		{
			"directories" : 
			[
				{
					"build" : ".",
					"childIndexes" : 
					[
						1,
						2,
						3
					],
					"jsonFile" : "directory-.-Debug-d0094a50bb2071803777.json",
					"minimumCMakeVersion" : 
					{
						"string" : "3.14"
					},
					"projectIndex" : 0,
					"source" : ".",
					"targetIndexes" : 
					[
						0,
						3,
						5
					]
				},
				{
					"build" : "_deps/spdlog-build",
					"jsonFile" : "directory-_deps.spdlog-build-Debug-59ade99d86cdbe321ad8.json",
					"minimumCMakeVersion" : 
					{
						"string" : "3.10"
					},
					"parentIndex" : 0,
					"projectIndex" : 1,
					"source" : "3rdParty/spdlog/be9796fe42cf4cd102be04c44dd3c83ff2a4d1c0",
					"targetIndexes" : 
					[
						1,
						6
					]
				},
				{
					"build" : "_deps/catch2-build",
					"jsonFile" : "directory-_deps.catch2-build-Debug-c42fa9fa2984683ac706.json",
					"minimumCMakeVersion" : 
					{
						"string" : "3.5"
					},
					"parentIndex" : 0,
					"projectIndex" : 2,
					"source" : "3rdParty/catch2/406a07db1ac202c2253293c0369ea576800cb47e",
					"targetIndexes" : 
					[
						2,
						4
					]
				},
				{
					"build" : "sample",
					"jsonFile" : "directory-sample-Debug-60460f4121510704294c.json",
					"minimumCMakeVersion" : 
					{
						"string" : "3.14"
					},
					"parentIndex" : 0,
					"projectIndex" : 0,
					"source" : "sample"
				}
			],
			"name" : "Debug",
			"projects" : 
			[
				{
					"childIndexes" : 
					[
						1,
						2
					],
					"directoryIndexes" : 
					[
						0,
						3
					],
					"name" : "Akie_musicplay",
					"targetIndexes" : 
					[
						0,
						3,
						5
					]
				},
				{
					"directoryIndexes" : 
					[
						1
					],
					"name" : "spdlog",
					"parentIndex" : 0,
					"targetIndexes" : 
					[
						1,
						6
					]
				},
				{
					"directoryIndexes" : 
					[
						2
					],
					"name" : "Catch2",
					"parentIndex" : 0,
					"targetIndexes" : 
					[
						2,
						4
					]
				}
			],
			"targets" : 
			[
				{
					"directoryIndex" : 0,
					"id" : "ALL_BUILD::@6890427a1f51a3e7e1df",
					"jsonFile" : "target-ALL_BUILD-Debug-d24c6ea49a0ab51cce08.json",
					"name" : "ALL_BUILD",
					"projectIndex" : 0
				},
				{
					"directoryIndex" : 1,
					"id" : "ALL_BUILD::@eb35cfce7893ccfeff1e",
					"jsonFile" : "target-ALL_BUILD-Debug-fa877d38c8eb6b7d55e4.json",
					"name" : "ALL_BUILD",
					"projectIndex" : 1
				},
				{
					"directoryIndex" : 2,
					"id" : "ALL_BUILD::@3e93893dc0618e684ae7",
					"jsonFile" : "target-ALL_BUILD-Debug-d7e98a217a88426099ea.json",
					"name" : "ALL_BUILD",
					"projectIndex" : 2
				},
				{
					"directoryIndex" : 0,
					"id" : "AkieMusicPlay::@6890427a1f51a3e7e1df",
					"jsonFile" : "target-AkieMusicPlay-Debug-62fc9108a5f50aa48200.json",
					"name" : "AkieMusicPlay",
					"projectIndex" : 0
				},
				{
					"directoryIndex" : 2,
					"id" : "Catch2WithMain::@3e93893dc0618e684ae7",
					"jsonFile" : "target-Catch2WithMain-Debug-ae077315fe7e146e8e3b.json",
					"name" : "Catch2WithMain",
					"projectIndex" : 2
				},
				{
					"directoryIndex" : 0,
					"id" : "ZERO_CHECK::@6890427a1f51a3e7e1df",
					"jsonFile" : "target-ZERO_CHECK-Debug-fd1f21aa03df062147a1.json",
					"name" : "ZERO_CHECK",
					"projectIndex" : 0
				},
				{
					"directoryIndex" : 1,
					"id" : "spdlog::@eb35cfce7893ccfeff1e",
					"jsonFile" : "target-spdlog-Debug-2946a17e175438e6731c.json",
					"name" : "spdlog",
					"projectIndex" : 1
				}
			]
		},
		{
			"directories" : 
			[
				{
					"build" : ".",
					"childIndexes" : 
					[
						1,
						2,
						3
					],
					"jsonFile" : "directory-.-Release-d0094a50bb2071803777.json",
					"minimumCMakeVersion" : 
					{
						"string" : "3.14"
					},
					"projectIndex" : 0,
					"source" : ".",
					"targetIndexes" : 
					[
						0,
						3,
						5
					]
				},
				{
					"build" : "_deps/spdlog-build",
					"jsonFile" : "directory-_deps.spdlog-build-Release-59ade99d86cdbe321ad8.json",
					"minimumCMakeVersion" : 
					{
						"string" : "3.10"
					},
					"parentIndex" : 0,
					"projectIndex" : 1,
					"source" : "3rdParty/spdlog/be9796fe42cf4cd102be04c44dd3c83ff2a4d1c0",
					"targetIndexes" : 
					[
						1,
						6
					]
				},
				{
					"build" : "_deps/catch2-build",
					"jsonFile" : "directory-_deps.catch2-build-Release-c42fa9fa2984683ac706.json",
					"minimumCMakeVersion" : 
					{
						"string" : "3.5"
					},
					"parentIndex" : 0,
					"projectIndex" : 2,
					"source" : "3rdParty/catch2/406a07db1ac202c2253293c0369ea576800cb47e",
					"targetIndexes" : 
					[
						2,
						4
					]
				},
				{
					"build" : "sample",
					"jsonFile" : "directory-sample-Release-60460f4121510704294c.json",
					"minimumCMakeVersion" : 
					{
						"string" : "3.14"
					},
					"parentIndex" : 0,
					"projectIndex" : 0,
					"source" : "sample"
				}
			],
			"name" : "Release",
			"projects" : 
			[
				{
					"childIndexes" : 
					[
						1,
						2
					],
					"directoryIndexes" : 
					[
						0,
						3
					],
					"name" : "Akie_musicplay",
					"targetIndexes" : 
					[
						0,
						3,
						5
					]
				},
				{
					"directoryIndexes" : 
					[
						1
					],
					"name" : "spdlog",
					"parentIndex" : 0,
					"targetIndexes" : 
					[
						1,
						6
					]
				},
				{
					"directoryIndexes" : 
					[
						2
					],
					"name" : "Catch2",
					"parentIndex" : 0,
					"targetIndexes" : 
					[
						2,
						4
					]
				}
			],
			"targets" : 
			[
				{
					"directoryIndex" : 0,
					"id" : "ALL_BUILD::@6890427a1f51a3e7e1df",
					"jsonFile" : "target-ALL_BUILD-Release-d24c6ea49a0ab51cce08.json",
					"name" : "ALL_BUILD",
					"projectIndex" : 0
				},
				{
					"directoryIndex" : 1,
					"id" : "ALL_BUILD::@eb35cfce7893ccfeff1e",
					"jsonFile" : "target-ALL_BUILD-Release-fa877d38c8eb6b7d55e4.json",
					"name" : "ALL_BUILD",
					"projectIndex" : 1
				},
				{
					"directoryIndex" : 2,
					"id" : "ALL_BUILD::@3e93893dc0618e684ae7",
					"jsonFile" : "target-ALL_BUILD-Release-d7e98a217a88426099ea.json",
					"name" : "ALL_BUILD",
					"projectIndex" : 2
				},
				{
					"directoryIndex" : 0,
					"id" : "AkieMusicPlay::@6890427a1f51a3e7e1df",
					"jsonFile" : "target-AkieMusicPlay-Release-7718cf8850ab3d766a63.json",
					"name" : "AkieMusicPlay",
					"projectIndex" : 0
				},
				{
					"directoryIndex" : 2,
					"id" : "Catch2WithMain::@3e93893dc0618e684ae7",
					"jsonFile" : "target-Catch2WithMain-Release-e15182d439d472c24226.json",
					"name" : "Catch2WithMain",
					"projectIndex" : 2
				},
				{
					"directoryIndex" : 0,
					"id" : "ZERO_CHECK::@6890427a1f51a3e7e1df",
					"jsonFile" : "target-ZERO_CHECK-Release-fd1f21aa03df062147a1.json",
					"name" : "ZERO_CHECK",
					"projectIndex" : 0
				},
				{
					"directoryIndex" : 1,
					"id" : "spdlog::@eb35cfce7893ccfeff1e",
					"jsonFile" : "target-spdlog-Release-88d7283f1c1a105d55e1.json",
					"name" : "spdlog",
					"projectIndex" : 1
				}
			]
		},
		{
			"directories" : 
			[
				{
					"build" : ".",
					"childIndexes" : 
					[
						1,
						2,
						3
					],
					"jsonFile" : "directory-.-MinSizeRel-d0094a50bb2071803777.json",
					"minimumCMakeVersion" : 
					{
						"string" : "3.14"
					},
					"projectIndex" : 0,
					"source" : ".",
					"targetIndexes" : 
					[
						0,
						3,
						5
					]
				},
				{
					"build" : "_deps/spdlog-build",
					"jsonFile" : "directory-_deps.spdlog-build-MinSizeRel-59ade99d86cdbe321ad8.json",
					"minimumCMakeVersion" : 
					{
						"string" : "3.10"
					},
					"parentIndex" : 0,
					"projectIndex" : 1,
					"source" : "3rdParty/spdlog/be9796fe42cf4cd102be04c44dd3c83ff2a4d1c0",
					"targetIndexes" : 
					[
						1,
						6
					]
				},
				{
					"build" : "_deps/catch2-build",
					"jsonFile" : "directory-_deps.catch2-build-MinSizeRel-c42fa9fa2984683ac706.json",
					"minimumCMakeVersion" : 
					{
						"string" : "3.5"
					},
					"parentIndex" : 0,
					"projectIndex" : 2,
					"source" : "3rdParty/catch2/406a07db1ac202c2253293c0369ea576800cb47e",
					"targetIndexes" : 
					[
						2,
						4
					]
				},
				{
					"build" : "sample",
					"jsonFile" : "directory-sample-MinSizeRel-60460f4121510704294c.json",
					"minimumCMakeVersion" : 
					{
						"string" : "3.14"
					},
					"parentIndex" : 0,
					"projectIndex" : 0,
					"source" : "sample"
				}
			],
			"name" : "MinSizeRel",
			"projects" : 
			[
				{
					"childIndexes" : 
					[
						1,
						2
					],
					"directoryIndexes" : 
					[
						0,
						3
					],
					"name" : "Akie_musicplay",
					"targetIndexes" : 
					[
						0,
						3,
						5
					]
				},
				{
					"directoryIndexes" : 
					[
						1
					],
					"name" : "spdlog",
					"parentIndex" : 0,
					"targetIndexes" : 
					[
						1,
						6
					]
				},
				{
					"directoryIndexes" : 
					[
						2
					],
					"name" : "Catch2",
					"parentIndex" : 0,
					"targetIndexes" : 
					[
						2,
						4
					]
				}
			],
			"targets" : 
			[
				{
					"directoryIndex" : 0,
					"id" : "ALL_BUILD::@6890427a1f51a3e7e1df",
					"jsonFile" : "target-ALL_BUILD-MinSizeRel-d24c6ea49a0ab51cce08.json",
					"name" : "ALL_BUILD",
					"projectIndex" : 0
				},
				{
					"directoryIndex" : 1,
					"id" : "ALL_BUILD::@eb35cfce7893ccfeff1e",
					"jsonFile" : "target-ALL_BUILD-MinSizeRel-fa877d38c8eb6b7d55e4.json",
					"name" : "ALL_BUILD",
					"projectIndex" : 1
				},
				{
					"directoryIndex" : 2,
					"id" : "ALL_BUILD::@3e93893dc0618e684ae7",
					"jsonFile" : "target-ALL_BUILD-MinSizeRel-d7e98a217a88426099ea.json",
					"name" : "ALL_BUILD",
					"projectIndex" : 2
				},
				{
					"directoryIndex" : 0,
					"id" : "AkieMusicPlay::@6890427a1f51a3e7e1df",
					"jsonFile" : "target-AkieMusicPlay-MinSizeRel-d21feddd719f1de2b83f.json",
					"name" : "AkieMusicPlay",
					"projectIndex" : 0
				},
				{
					"directoryIndex" : 2,
					"id" : "Catch2WithMain::@3e93893dc0618e684ae7",
					"jsonFile" : "target-Catch2WithMain-MinSizeRel-bcd401a653fce6c3fbd2.json",
					"name" : "Catch2WithMain",
					"projectIndex" : 2
				},
				{
					"directoryIndex" : 0,
					"id" : "ZERO_CHECK::@6890427a1f51a3e7e1df",
					"jsonFile" : "target-ZERO_CHECK-MinSizeRel-fd1f21aa03df062147a1.json",
					"name" : "ZERO_CHECK",
					"projectIndex" : 0
				},
				{
					"directoryIndex" : 1,
					"id" : "spdlog::@eb35cfce7893ccfeff1e",
					"jsonFile" : "target-spdlog-MinSizeRel-4d9bcf7f08ef60f2da77.json",
					"name" : "spdlog",
					"projectIndex" : 1
				}
			]
		},
		{
			"directories" : 
			[
				{
					"build" : ".",
					"childIndexes" : 
					[
						1,
						2,
						3
					],
					"jsonFile" : "directory-.-RelWithDebInfo-d0094a50bb2071803777.json",
					"minimumCMakeVersion" : 
					{
						"string" : "3.14"
					},
					"projectIndex" : 0,
					"source" : ".",
					"targetIndexes" : 
					[
						0,
						3,
						5
					]
				},
				{
					"build" : "_deps/spdlog-build",
					"jsonFile" : "directory-_deps.spdlog-build-RelWithDebInfo-59ade99d86cdbe321ad8.json",
					"minimumCMakeVersion" : 
					{
						"string" : "3.10"
					},
					"parentIndex" : 0,
					"projectIndex" : 1,
					"source" : "3rdParty/spdlog/be9796fe42cf4cd102be04c44dd3c83ff2a4d1c0",
					"targetIndexes" : 
					[
						1,
						6
					]
				},
				{
					"build" : "_deps/catch2-build",
					"jsonFile" : "directory-_deps.catch2-build-RelWithDebInfo-c42fa9fa2984683ac706.json",
					"minimumCMakeVersion" : 
					{
						"string" : "3.5"
					},
					"parentIndex" : 0,
					"projectIndex" : 2,
					"source" : "3rdParty/catch2/406a07db1ac202c2253293c0369ea576800cb47e",
					"targetIndexes" : 
					[
						2,
						4
					]
				},
				{
					"build" : "sample",
					"jsonFile" : "directory-sample-RelWithDebInfo-60460f4121510704294c.json",
					"minimumCMakeVersion" : 
					{
						"string" : "3.14"
					},
					"parentIndex" : 0,
					"projectIndex" : 0,
					"source" : "sample"
				}
			],
			"name" : "RelWithDebInfo",
			"projects" : 
			[
				{
					"childIndexes" : 
					[
						1,
						2
					],
					"directoryIndexes" : 
					[
						0,
						3
					],
					"name" : "Akie_musicplay",
					"targetIndexes" : 
					[
						0,
						3,
						5
					]
				},
				{
					"directoryIndexes" : 
					[
						1
					],
					"name" : "spdlog",
					"parentIndex" : 0,
					"targetIndexes" : 
					[
						1,
						6
					]
				},
				{
					"directoryIndexes" : 
					[
						2
					],
					"name" : "Catch2",
					"parentIndex" : 0,
					"targetIndexes" : 
					[
						2,
						4
					]
				}
			],
			"targets" : 
			[
				{
					"directoryIndex" : 0,
					"id" : "ALL_BUILD::@6890427a1f51a3e7e1df",
					"jsonFile" : "target-ALL_BUILD-RelWithDebInfo-d24c6ea49a0ab51cce08.json",
					"name" : "ALL_BUILD",
					"projectIndex" : 0
				},
				{
					"directoryIndex" : 1,
					"id" : "ALL_BUILD::@eb35cfce7893ccfeff1e",
					"jsonFile" : "target-ALL_BUILD-RelWithDebInfo-fa877d38c8eb6b7d55e4.json",
					"name" : "ALL_BUILD",
					"projectIndex" : 1
				},
				{
					"directoryIndex" : 2,
					"id" : "ALL_BUILD::@3e93893dc0618e684ae7",
					"jsonFile" : "target-ALL_BUILD-RelWithDebInfo-d7e98a217a88426099ea.json",
					"name" : "ALL_BUILD",
					"projectIndex" : 2
				},
				{
					"directoryIndex" : 0,
					"id" : "AkieMusicPlay::@6890427a1f51a3e7e1df",
					"jsonFile" : "target-AkieMusicPlay-RelWithDebInfo-83d454e659bbb28bb463.json",
					"name" : "AkieMusicPlay",
					"projectIndex" : 0
				},
				{
					"directoryIndex" : 2,
					"id" : "Catch2WithMain::@3e93893dc0618e684ae7",
					"jsonFile" : "target-Catch2WithMain-RelWithDebInfo-c2e7b562911ea20aef12.json",
					"name" : "Catch2WithMain",
					"projectIndex" : 2
				},
				{
					"directoryIndex" : 0,
					"id" : "ZERO_CHECK::@6890427a1f51a3e7e1df",
					"jsonFile" : "target-ZERO_CHECK-RelWithDebInfo-fd1f21aa03df062147a1.json",
					"name" : "ZERO_CHECK",
					"projectIndex" : 0
				},
				{
					"directoryIndex" : 1,
					"id" : "spdlog::@eb35cfce7893ccfeff1e",
					"jsonFile" : "target-spdlog-RelWithDebInfo-0ce20b276200ca45e8ac.json",
					"name" : "spdlog",
					"projectIndex" : 1
				}
			]
		}
	],
	"kind" : "codemodel",
	"paths" : 
	{
		"build" : "E:/software/Code/AkieMusicPlay/build",
		"source" : "E:/software/Code/AkieMusicPlay"
	},
	"version" : 
	{
		"major" : 2,
		"minor" : 6
	}
}
